encoderx/__init__.py
encoderx/encoder.py
encoderx-0.0.0.1.dist-info/LICENCE.txt
encoderx-0.0.0.1.dist-info/METADATA
encoderx-0.0.0.1.dist-info/WHEEL
encoderx-0.0.0.1.dist-info/top_level.txt
encoderx-0.0.0.1.dist-info/RECORD
