Metadata-Version: 2.1
Name: encoderx
Version: 0.0.0.1
Summary: Python library to encoderbox from Delta X Robot
Home-page: https://github.com/VanThanBK/python-encoderx
Author: Than Nguyen
Author-email: jonyvanthan@gmail.com
License: UNKNOWN
Project-URL: Bug Tracker, https://github.com/VanThanBK/python-encoderx
Platform: UNKNOWN
Classifier: Programming Language :: Python :: 3
Classifier: License :: OSI Approved :: MIT License
Classifier: Operating System :: OS Independent
Requires-Python: >=3.6
License-File: LICENCE.txt
